wgop_filler/__init__.py
wgop_filler/main.py
wgop_filler/src/__init__.py
wgop_filler/src/author
wgop_filler/src/filler.py
wgop_filler-0.1.20.dist-info/METADATA
wgop_filler-0.1.20.dist-info/WHEEL
wgop_filler-0.1.20.dist-info/entry_points.txt
wgop_filler-0.1.20.dist-info/top_level.txt
wgop_filler-0.1.20.dist-info/RECORD
