Metadata-Version: 2.1
Name: wgop-filler
Version: 0.1.20
Summary: 42filler
Home-page: UNKNOWN
Author: wgop team
License: UNKNOWN
Platform: UNKNOWN
Requires-Python: >=3.8,<4.0
